ukpopulation/__init__.py
ukpopulation/myedata.py
ukpopulation/nppdata.py
ukpopulation/snppdata.py
ukpopulation/utils.py
ukpopulation-1.0.3.dist-info/METADATA
ukpopulation-1.0.3.dist-info/RECORD
ukpopulation-1.0.3.dist-info/WHEEL
ukpopulation-1.0.3.dist-info/top_level.txt
