Metadata-Version: 2.1
Name: ukpopulation
Version: 1.0.3
Summary: Download, cache, collate, filter and extrapolate UK Population estimates and projections
Home-page: https://github.com/nismod/ukpopulation
Author: Andrew P Smith, Tom Russell
Author-email: a.p.smith@leeds.ac.uk, tom.russell@ouce.ox.ac.uk
License: UNKNOWN
Platform: UNKNOWN
Classifier: Programming Language :: Python :: 3
Classifier: License :: OSI Approved :: MIT License
Classifier: Operating System :: OS Independent
Requires-Dist: numpy
Requires-Dist: pandas
Requires-Dist: requests
Requires-Dist: openpyxl
Requires-Dist: beautifulsoup4
Requires-Dist: lxml
Requires-Dist: ukcensusapi
